lost_ds/__init__.py
lost_ds/compat.py
lost_ds/copy.py
lost_ds/core.py
lost_ds/im_util.py
lost_ds/scheduler.py
lost_ds/util.py
lost_ds/cropping/__init__.py
lost_ds/cropping/api.py
lost_ds/cropping/cropping.py
lost_ds/cropping/ds_cropper.py
lost_ds/detection/__init__.py
lost_ds/detection/api.py
lost_ds/detection/bbox_merge.py
lost_ds/detection/detection.py
lost_ds/experimental/__init__.py
lost_ds/functional/__init__.py
lost_ds/functional/api.py
lost_ds/functional/filter.py
lost_ds/functional/mapping.py
lost_ds/functional/split.py
lost_ds/functional/transform.py
lost_ds/functional/validation.py
lost_ds/geometry/__init__.py
lost_ds/geometry/api.py
lost_ds/geometry/bbox.py
lost_ds/geometry/geometry.py
lost_ds/geometry/line.py
lost_ds/geometry/lost_geom.py
lost_ds/geometry/point.py
lost_ds/geometry/polygon.py
lost_ds/io/__init__.py
lost_ds/io/file_man.py
lost_ds/masking/__init__.py
lost_ds/masking/api.py
lost_ds/masking/masking.py
lost_ds/reporting/__init__.py
lost_ds/segmentation/__init__.py
lost_ds/segmentation/anno_from_seg.py
lost_ds/segmentation/api.py
lost_ds/segmentation/instance_seg.py
lost_ds/segmentation/panoptic_seg.py
lost_ds/segmentation/semantic_seg.py
lost_ds/vis/__init__.py
lost_ds/vis/api.py
lost_ds/vis/geometries.py
lost_ds/vis/vis.py
lost_ds-1.2.0.dist-info/METADATA
lost_ds-1.2.0.dist-info/WHEEL
lost_ds-1.2.0.dist-info/licenses/LICENSE
lost_ds-1.2.0.dist-info/RECORD
